.gitignore
MANIFEST.in
README.rst
bootstrap.py
buildout.cfg
setup.cfg
setup.py
docs/HISTORY.txt
docs/INSTALL.txt
docs/LICENSE.GPL
docs/LICENSE.txt
raptus/__init__.py
raptus.mailchimp.egg-info/PKG-INFO
raptus.mailchimp.egg-info/SOURCES.txt
raptus.mailchimp.egg-info/dependency_links.txt
raptus.mailchimp.egg-info/entry_points.txt
raptus.mailchimp.egg-info/namespace_packages.txt
raptus.mailchimp.egg-info/not-zip-safe
raptus.mailchimp.egg-info/requires.txt
raptus.mailchimp.egg-info/top_level.txt
raptus/mailchimp/__init__.py
raptus/mailchimp/configure.zcml
raptus/mailchimp/connector.py
raptus/mailchimp/interfaces.py
raptus/mailchimp/rebuild_i18n.sh
raptus/mailchimp/setuphandlers.py
raptus/mailchimp/tests.py
raptus/mailchimp/upgrades.py
raptus/mailchimp/upgrades.zcml
raptus/mailchimp/Extensions/__init__.py
raptus/mailchimp/Extensions/install.py
raptus/mailchimp/browser/__init__.py
raptus/mailchimp/browser/configlet.pt
raptus/mailchimp/browser/configlet.py
raptus/mailchimp/browser/configure.zcml
raptus/mailchimp/browser/icon.gif
raptus/mailchimp/browser/portlet.pt
raptus/mailchimp/browser/portlet.py
raptus/mailchimp/browser/subscriber.pt
raptus/mailchimp/browser/subscriber.py
raptus/mailchimp/browser/subscriber_message.pt
raptus/mailchimp/locales/raptus.mailchimp.pot
raptus/mailchimp/locales/de/LC_MESSAGES/raptus.mailchimp.mo
raptus/mailchimp/locales/fr/LC_MESSAGES/raptus.mailchimp.mo
raptus/mailchimp/profiles/default/controlpanel.xml
raptus/mailchimp/profiles/default/metadata.xml
raptus/mailchimp/profiles/default/portlets.xml
raptus/mailchimp/profiles/default/propertiestool.xml
raptus/mailchimp/profiles/default/raptus.mailchimp_setupProperties.txt