Metadata-Version: 1.1
Name: raptus.mailchimp
Version: 1.1
Summary: MailChimp plone integration
Home-page: https://github.com/Raptus/raptus.mailchimp
Author: Raptus AG
Author-email: dev@raptus.com
License: GPL
Platform: UNKNOWN
Classifier: Framework :: Plone
Classifier: Programming Language :: Python
